.travis.yml
LICENSE
MANIFEST.in
README.rst
setup.py
Mopidy_VKontakte.egg-info/PKG-INFO
Mopidy_VKontakte.egg-info/SOURCES.txt
Mopidy_VKontakte.egg-info/dependency_links.txt
Mopidy_VKontakte.egg-info/entry_points.txt
Mopidy_VKontakte.egg-info/not-zip-safe
Mopidy_VKontakte.egg-info/requires.txt
Mopidy_VKontakte.egg-info/top_level.txt
mopidy_vkontakte/__init__.py
mopidy_vkontakte/actor.py
mopidy_vkontakte/ext.conf
mopidy_vkontakte/library.py
mopidy_vkontakte/playlists.py
mopidy_vkontakte/session.py
tests/__init__.py
tests/test_extension.py