Metadata-Version: 1.1
Name: Mopidy-VKontakte
Version: 0.2.0
Summary: Mopidy extension for VKontakte allows         to listen to music from VKontakte social network.
Home-page: https://github.com/sibuser/mopidy-vkontakte
Author: Alexey Ulyanov
Author-email: sibuser.nsk@gmail.com
License: Apache License, Version 2.0
Platform: UNKNOWN
Classifier: Environment :: No Input/Output (Daemon)
Classifier: Intended Audience :: End Users/Desktop
Classifier: License :: OSI Approved :: Apache Software License
Classifier: Operating System :: OS Independent
Classifier: Programming Language :: Python :: 2
Classifier: Topic :: Multimedia :: Sound/Audio :: Players
